amispy/__init__.py
amispy/base/__init__.py
amispy/base/api.py
amispy/base/base.py
amispy/components/__init__.py
amispy/components/action.py
amispy/components/app_page.py
amispy/components/chart.py
amispy/components/crud.py
amispy/components/page.py
amispy/components/service.py
amispy/components/form/__init__.py
amispy/components/form/form.py
amispy/components/form/formarray.py
amispy/components/form/formdate.py
amispy/components/form/formdaterange.py
amispy/components/form/formdatetime.py
amispy/components/form/formdatetimerange.py
amispy/components/form/formeditor.py
amispy/components/form/formitem.py
amispy/components/form/formlocation.py
amispy/components/form/formmonth.py
amispy/components/form/formmonthrange.py
amispy/components/form/formradios.py
amispy/components/form/formselect.py
amispy/components/form/formtext.py
amispy/components/form/formtextarea.py
amispy-0.0.3.dist-info/LICENSE
amispy-0.0.3.dist-info/METADATA
amispy-0.0.3.dist-info/WHEEL
amispy-0.0.3.dist-info/top_level.txt
amispy-0.0.3.dist-info/RECORD
